LICENSE
README.md
setup.py
sherlock_lib/__init__.py
sherlock_lib.egg-info/PKG-INFO
sherlock_lib.egg-info/SOURCES.txt
sherlock_lib.egg-info/dependency_links.txt
sherlock_lib.egg-info/requires.txt
sherlock_lib.egg-info/top_level.txt
sherlock_lib/controllers/__init__.py
sherlock_lib/controllers/sherlock.py
sherlock_lib/controllers/sherlock_future_session.py
sherlock_lib/controllers/sherlock_get_response.py
sherlock_lib/controllers/sherlock_interpolate_string.py
sherlock_lib/controllers/sherlock_search_target.py
sherlock_lib/models/__init__.py
sherlock_lib/models/query_notify.py
sherlock_lib/models/query_notify_dict.py
sherlock_lib/models/query_result.py
sherlock_lib/models/query_status.py
sherlock_lib/models/site_information.py
sherlock_lib/models/sites_information.py
sherlock_lib/tests/__init__.py
sherlock_lib/tests/all.py
sherlock_lib/tests/base.py
sherlock_lib/tests/test_multiple_usernames.py