Metadata-Version: 2.1
Name: sherlock-lib
Version: 0.0.5
Summary: 🔎 Hunt down social media accounts by username across social networks
Author: Paulo Ricardo Mesquita
Author-email: pauloricardomrs2002@gmail.com
License: MIT License
Keywords: sherlock,stalking,sherlock lib,sherlock-lib
License-File: LICENSE
